Workbook

Sheet Status
B2: New Deal Owner | C2: Strategic AM | D2: Non Strategic AM | E2: AM Accounts | F2: Non-Strategic Deals to Close | G2: Strategic Deals to Close | H2: Total Accounts | J2: Strategic Partners
B3: Daniela Reyes | C3: =countifs('All partners'!$G:$G,$B3,'All partners'!$F:$F,"Account Management",'All partners'!$H:$H,TRUE) -> 16 | D3: =countifs('All partners'!$G:$G,$B3,'All partners'!$F:$F,"Account Management",'All partners'!$H:$H,FALSE) -> 23 | E3: 1 | F3: =countifs('All partners'!$G:$G,$B3,'All partners'!$F:$F,"Business Development",'All partners'!$H:$H,FALSE) -> 28 | G3: =countifs('All partners'!$G:$G,$B3,'All partners'!$F:$F,"Business Development",'All partners'!$H:$H,TRUE) -> 10 | H3: =sum(E3:G3) -> 39 | J3: Door Openers, Ahead of the Curve, Innovators, Local Must-Have, Regulators
B4: Johanderson Guevara | C4: =countifs('All partners'!$G:$G,$B4,'All partners'!$F:$F,"Account Management",'All partners'!$H:$H,TRUE) -> 19 | D4: =countifs('All partners'!$G:$G,$B4,'All partners'!$F:$F,"Account Management",'All partners'!$H:$H,FALSE) -> 22 | E4: =sum(C4:D4) -> 41 | F4: =countifs('All partners'!$G:$G,$B4,'All partners'!$F:$F,"Business Development",'All partners'!$H:$H,FALSE) -> 13 | G4: =countifs('All partners'!$G:$G,$B4,'All partners'!$F:$F,"Business Development",'All partners'!$H:$H,TRUE) -> 10 | H4: =sum(E4:G4) -> 64 | I4: =(H4-F4) -> 51
B5: Talita Diaz Gama | C5: =countifs('All partners'!$G:$G,$B5,'All partners'!$F:$F,"Account Management",'All partners'!$H:$H,TRUE) -> 20 | D5: =countifs('All partners'!$G:$G,$B5,'All partners'!$F:$F,"Account Management",'All partners'!$H:$H,FALSE) -> 22 | E5: =sum(C5:D5) -> 42 | F5: =countifs('All partners'!$G:$G,$B5,'All partners'!$F:$F,"Business Development",'All partners'!$H:$H,FALSE) -> 22 | G5: =countifs('All partners'!$G:$G,$B5,'All partners'!$F:$F,"Business Development",'All partners'!$H:$H,TRUE) -> 16 | H5: =sum(E5:G5) -> 80 | I5: =(H5-F5) -> 58 | J5: Tier 1 : Strong Demand
B6: Mariana Castellanos | C6: =countifs('All partners'!$G:$G,$B6,'All partners'!$F:$F,"Account Management",'All partners'!$H:$H,TRUE) -> 0 | D6: =countifs('All partners'!$G:$G,$B6,'All partners'!$F:$F,"Account Management",'All partners'!$H:$H,FALSE) -> 0 | E6: =sum(C6:D6) -> 0 | F6: =countifs('All partners'!$G:$G,$B6,'All partners'!$F:$F,"Business Development",'All partners'!$H:$H,FALSE) -> 0 | G6: =countifs('All partners'!$G:$G,$B6,'All partners'!$F:$F,"Business Development",'All partners'!$H:$H,TRUE) -> 0 | H6: =sum(E6:G6) -> 0 | I6: =(H6-F6) -> 0 | J6: Strong local footprint as top payment provider locally. Popular by Merchant Demand
B7: Francisco Quintana | C7: =countifs('All partners'!$G:$G,$B7,'All partners'!$F:$F,"Account Management",'All partners'!$H:$H,TRUE) -> 4 | D7: =countifs('All partners'!$G:$G,$B7,'All partners'!$F:$F,"Account Management",'All partners'!$H:$H,FALSE) -> 14 | E7: =sum(C7:D7) -> 18 | F7: =countifs('All partners'!$G:$G,$B7,'All partners'!$F:$F,"Business Development",'All partners'!$H:$H,FALSE) -> 26 | G7: =countifs('All partners'!$G:$G,$B7,'All partners'!$F:$F,"Business Development",'All partners'!$H:$H,TRUE) -> 7 | H7: =sum(E7:G7) -> 51 | I7: =(H7-F7) -> 25
B8: Alessandra Rospigliosi | C8: =countifs('All partners'!$G:$G,$B8,'All partners'!$F:$F,"Account Management",'All partners'!$H:$H,TRUE) -> 17 | D8: =countifs('All partners'!$G:$G,$B8,'All partners'!$F:$F,"Account Management",'All partners'!$H:$H,FALSE) -> 23 | E8: =sum(C8:D8) -> 40 | F8: =countifs('All partners'!$G:$G,$B8,'All partners'!$F:$F,"Business Development",'All partners'!$H:$H,FALSE) -> 57 | G8: =countifs('All partners'!$G:$G,$B8,'All partners'!$F:$F,"Business Development",'All partners'!$H:$H,TRUE) -> 5 | H8: =sum(E8:G8) -> 102 | I8: =(H8-F8) -> 45 | J8: Tier 2 Partners (Country/Region Specific)
B9: Franklin | C9: =countifs('All partners'!$G:$G,$B9,'All partners'!$F:$F,"Account Management",'All partners'!$H:$H,TRUE) -> 0 | D9: =countifs('All partners'!$G:$G,$B9,'All partners'!$F:$F,"Account Management",'All partners'!$H:$H,FALSE) -> 0 | E9: =sum(C9:D9) -> 0 | F9: =countifs('All partners'!$G:$G,$B9,'All partners'!$F:$F,"Business Development",'All partners'!$H:$H,FALSE) -> 0 | G9: =countifs('All partners'!$G:$G,$B9,'All partners'!$F:$F,"Business Development",'All partners'!$H:$H,TRUE) -> 0 | H9: =sum(E9:G9) -> 0 | I9: =(H9-F9) -> 0 | J9: Payplug (EU), Yape (PE), Redeban (CO)
B10: Europe | C10: =countifs('All partners'!$G:$G,$B10,'All partners'!$F:$F,"Account Management",'All partners'!$H:$H,TRUE) -> 0 | D10: =countifs('All partners'!$G:$G,$B10,'All partners'!$F:$F,"Account Management",'All partners'!$H:$H,FALSE) -> 0 | E10: =sum(C10:D10) -> 0 | F10: =countifs('All partners'!$G:$G,$B10,'All partners'!$F:$F,"Business Development",'All partners'!$H:$H,FALSE) -> 0 | G10: =countifs('All partners'!$G:$G,$B10,'All partners'!$F:$F,"Business Development",'All partners'!$H:$H,TRUE) -> 0 | H10: =sum(E10:G10) -> 0 | I10: =(H10-F10) -> 0
B11: Not assigned | C11: =countifs('All partners'!$G:$G,$B11,'All partners'!$F:$F,"Account Management",'All partners'!$H:$H,TRUE) -> 1 | D11: =countifs('All partners'!$G:$G,$B11,'All partners'!$F:$F,"Account Management",'All partners'!$H:$H,FALSE) -> 8 | E11: =sum(C11:D11) -> 9 | F11: =countifs('All partners'!$G:$G,$B11,'All partners'!$F:$F,"Business Development",'All partners'!$H:$H,FALSE) -> 39 | G11: =countifs('All partners'!$G:$G,$B11,'All partners'!$F:$F,"Business Development",'All partners'!$H:$H,TRUE) -> 1 | H11: =sum(E11:G11) -> 49 | I11: =(H11-F11) -> 10
B12: Total | C12: =sum(C3:C11) -> 77 | D12: =sum(D3:D11) -> 112 | E12: =sum(C12:D12) -> 189 | F12: =sum(F3:F11) -> 185 | G12: =sum(G3:G11) -> 49 | H12: =sum(H3:H11) -> 385
J13: Tier 3 Partners
C14: =C5+G5 -> 36
J16: High Risk Partners
J17: Astropay, Bayonet, Belvo, Cielo, Circle, Conekta, D24, Epoch, Fintoc, Flutterwave, Ibex, Khipu, Kount, PayU, Kushki, LexisNexis, Mercado Pago, Monnet Payments, Niubiz, OpenPay Mexico, PagSeguro Internacional, PagSmile, PayCash, PayPhone, PayPlug, PayRetailers, PaySafe, PayValida, Pinbank, Rocketfuel, SafetyPay, Shift4, STP, Unico, Unlimit, Vesta, OKTO Payment
J19: Others: Partners outside Acquirers, PSPs, APMs

Sheet Defined Partner Tiers
A1: Partner Tier | B1: Description/ Definition | C1: Engagement Model: | D1: Contracts | E1: Examples
A2: Strategic Partners: Very important | B2: - Deep technical and commercial integration - Executive-level sponsorship on both sides - Joint roadmap planning and co-innovation - Significant revenue impact or platform dependency | C2: - Dedicated partner manager - Regular Cadence - Quarterly executive business reviews - Joint GTM, marketing, and product initiatives | D2: Must- Have Length: Yuno to remain flexible & adapt to strategic partner | E2: Checkout Stripe dLocal
A3: Tier 1: Important | B3: - High-value/ High Demand (Local Popular Payment Method) - Scalable partners that materially contribute to revenue, - Must have for Geographic Expansion | C3: - Dedicated partner manager - Regular Cadence - Quarterly executive business reviews - Joint GTM, marketing, and product initiatives - Performance-based growth plans (Joint KPIs)
A4: Tier 2: Specific to a vertical or country (light touch) | B4: - Tactical or niche value - Moderate transaction volume - Limited roadmap alignment - Opportunity-driven engagement | C4: - Dedicated Owner - Monthly Cadence - Quarterly or Bi-Annual Business Reviews - GTM only if Vertical-specific w/ Commercial Teams
A5: Tier 3: Not relevant for wider Yuno (light touch) | B5: - Partners are transactional or experimental partners that provide optional capabilities with: - low volume, - limited engagement, and - minimal operational dependency | C5: - Self-service or automated support - Dedicated Owner (low touch) - Periodic health checks only - Review potential exit criteria 2x year (house keeping)
A6: Non-managed partners (we need to find a home) | B6: Fraud, 3Ds, PayOuts, PlugIns, KYC etc

Sheet All partners
A1: Provider | B1: Country | C1: Region | D1: Deal Stage | E1: Partner offering (acquirer, APM, Fraud etc) | F1: Type of Management | G1: Partner Manager | H1: Strategic? | I1: NDA Signed and in drive | J1: KYP Status | K1: Integration Ready by Yuno | L1: Integration Used by Merchants | M1: Revshare Contract | N1: Revshare active | O1: Review to kill agreement | P1: Type of Partner | Q1: Salesforce | R1: Airtable | S1: Reports | T1: Invoice Rev Share | U1: Pricing Requests | W1: Comments | X1: Account Plan
A2: 2C2P / Ant Intl | B2: Global | C2: APAC | D2: Agreement Signed | E2: Acquirer | F2: Account Management | G2: Lily/ Daniela | H2: TRUE | I2: FALSE | J2: FALSE | K2: FALSE | L2: FALSE | M2: TRUE | N2: FALSE | O2: FALSE | P2: Strategic Partners: Very Important | Q2: FALSE | R2: TRUE | S2: FALSE | T2: FALSE
A3: 54pay/PayGate | B3: Regional | C3: Africa | D3: Agreement Signed | E3: PSP/Aggregator | F3: Account Management | G3: Alessandra Rospigliosi | H3: FALSE | I3: TRUE | J3: FALSE | K3: FALSE | L3: FALSE | M3: TRUE | N3: FALSE | O3: FALSE | P3: Tier 3 Partners | Q3: FALSE | R3: FALSE | S3: FALSE | T3: FALSE
A4: ABSA Bank | B4: Regional | C4: EMEA | D4: Opportunity Identification | E4: Acquirer | F4: Business Development | G4: Alessandra Rospigliosi | H4: FALSE | I4: FALSE | J4: FALSE | K4: FALSE | L4: FALSE | M4: FALSE | N4: FALSE | O4: FALSE | P4: Tier 2 Partners | Q4: FALSE | R4: FALSE | S4: FALSE | T4: FALSE | W4: [Space X project, Africa]
A5: Accertify | B5: Global | C5: Global | D5: Initial Negotiation | E5: Fraud Provider | F5: Business Development | G5: Daniela Reyes | H5: FALSE | I5: TRUE | J5: FALSE | K5: FALSE | L5: FALSE | M5: FALSE | N5: FALSE | O5: FALSE | P5: Tier 3 Partners | Q5: FALSE | R5: FALSE | S5: FALSE | T5: FALSE | W5: Quieren firmar agreement solo cuando tengamos caso de uso
A6: Acuotaz | B6: Peru | C6: LATAM | D6: Opportunity Identification | E6: Other | F6: Business Development | G6: Talita Diaz Gama | H6: FALSE | I6: FALSE | J6: FALSE | K6: TRUE | L6: TRUE | M6: FALSE | N6: FALSE | O6: TRUE | P6: Tier 3 Partners | Q6: TRUE | R6: TRUE | S6: FALSE | T6: FALSE | W6: BNPL - not relevant
A7: Addi | B7: Colombia | C7: LATAM | D7: Live Partner | E7: APM | F7: Account Management | G7: Talita Diaz Gama | H7: FALSE | I7: FALSE | J7: FALSE | K7: TRUE | L7: TRUE | M7: TRUE | N7: FALSE | O7: FALSE | P7: Tier 2 Partners | Q7: TRUE | R7: TRUE | S7: FALSE | T7: FALSE
A8: Adiq Pagamentos | B8: Brasil | C8: Brasil | D8: Opportunity Identification | E8: Acquirer | F8: Business Development | G8: Johanderson Guevara | H8: FALSE | I8: FALSE | J8: FALSE | K8: FALSE | L8: FALSE | M8: FALSE | N8: FALSE | O8: FALSE | P8: Tier 3 Partners | Q8: TRUE | R8: FALSE | S8: FALSE | T8: FALSE
A9: Adyen | B9: Global | C9: Global | D9: Live Partner | E9: Acquirer | F9: Business Development | G9: Daniela Reyes | H9: TRUE | I9: FALSE | J9: FALSE | K9: TRUE | L9: TRUE | M9: FALSE | N9: FALSE | O9: FALSE | P9: Tier 1 Partners (Global) | Q9: TRUE | R9: TRUE | S9: FALSE | T9: FALSE | V9: Airtable by Ale | W9: Adyen debe de pasar a la getnet de Europa
A10: Afirme | B10: Mexico | C10: North America | D10: Agreement Signed | E10: Acquirer | F10: Account Management | G10: Daniela Reyes | H10: FALSE | I10: FALSE | J10: FALSE | K10: TRUE | L10: TRUE | M10: TRUE | N10: TRUE | O10: FALSE | P10: Tier 3 Partners | Q10: TRUE | R10: TRUE | S10: FALSE | T10: FALSE | V10: Afirme works through our Prosa integration.
A11: Aiia by Mastercard | B11: Regional | C11: EMEA | D11: Opportunity Identification | E11: APM | F11: Business Development | G11: Alessandra Rospigliosi | H11: FALSE | I11: FALSE | J11: FALSE | K11: FALSE | L11: FALSE | M11: FALSE | N11: FALSE | O11: FALSE | P11: Tier 1 Partners | Q11: FALSE | R11: FALSE | S11: FALSE | T11: FALSE | W11: Open Banking
A12: Airwallex APAC | B12: Global | C12: Global | D12: Live Partner | E12: Acquirer | F12: Account Management | G12: Alessandra Rospigliosi | H12: TRUE | I12: FALSE | J12: FALSE | K12: FALSE | L12: FALSE | M12: TRUE | N12: FALSE | O12: FALSE | P12: Strategic Partners: Very Important | Q12: FALSE
A13: Airwallex USA/ LATAM | B13: USA | C13: North America | D13: Agreement Signed | E13: Acquirer | F13: Account Management | G13: Daniela Reyes | H13: TRUE | I13: FALSE | J13: FALSE | K13: FALSE | L13: FALSE | M13: FALSE | N13: FALSE | O13: FALSE | P13: Strategic Partners: Very Important | Q13: FALSE | R13: FALSE | S13: FALSE | T13: FALSE
A14: Alelo Brasil | B14: Brasil | C14: Brasil | D14: Live Partner | E14: APM | F14: Account Management | G14: Johanderson Guevara | H14: FALSE | I14: FALSE | J14: FALSE | K14: TRUE | L14: TRUE | M14: FALSE | N14: FALSE | O14: TRUE | P14: Tier 2 Partners | Q14: TRUE | R14: TRUE | S14: FALSE | T14: FALSE
A15: Alignet | B15: Peru | C15: LATAM | D15: Agreement Signed | E15: PSP/Aggregator | F15: Account Management | G15: Talita Diaz Gama | H15: FALSE | I15: FALSE | J15: FALSE | K15: FALSE | L15: FALSE | M15: TRUE | N15: FALSE | O15: FALSE | P15: Tier 3 Partners | Q15: TRUE | R15: TRUE | W15: acquirer/BNPL - They have operations in mmore LATAM countries
A16: AllinPay (International) | B16: Regional | C16: APAC | D16: Agreement Review | E16: PSP/Aggregator | F16: Business Development | G16: Lily/ Daniela | H16: FALSE | I16: FALSE | J16: FALSE | K16: FALSE | L16: FALSE | M16: FALSE | N16: FALSE | O16: FALSE | P16: Tier 2 Partners | Q16: FALSE | R16: FALSE | S16: FALSE | T16: FALSE
A17: Amazon Pay | B17: Global | C17: Global | D17: Initial Negotiation | E17: PSP/Aggregator | F17: Business Development | G17: Alessandra Rospigliosi | H17: FALSE | I17: TRUE | J17: FALSE | K17: FALSE | L17: FALSE | M17: FALSE | N17: FALSE | O17: FALSE | P17: Tier 2 Partners | Q17: FALSE | R17: FALSE | S17: FALSE | T17: FALSE | W17: They are changing their complete strategy and they want to continue conversations in two months - February (12.01)
A18: American Express | B18: Global | C18: Global | D18: Agreement Review | E18: Acquirer | F18: Business Development | G18: Daniela Reyes | H18: TRUE | I18: FALSE | J18: FALSE | K18: FALSE | L18: FALSE | M18: FALSE | N18: FALSE | O18: FALSE | P18: Strategic Partners: Very Important | Q18: FALSE | R18: FALSE | S18: FALSE | T18: FALSE | W18: They will never have a revsahre
A19: Aplazo | B19: Mexico | C19: North America | D19: Agreement Signed | E19: Acquirer | F19: Account Management | G19: Daniela Reyes | H19: FALSE | I19: FALSE | J19: FALSE | K19: FALSE | L19: FALSE | M19: TRUE | N19: FALSE | O19: FALSE | P19: Tier 3 Partners | Q19: TRUE | R19: TRUE | S19: FALSE | T19: FALSE | V19: Airtable by Ale
A20: Apple Pay | B20: Global | C20: Global | D20: Live Partner | E20: APM | F20: Account Management | G20: Daniela Reyes | H20: TRUE | I20: FALSE | J20: FALSE | K20: TRUE | L20: TRUE | M20: FALSE | N20: FALSE | O20: FALSE | P20: Tier 1 Partners | Q20: TRUE | R20: TRUE | S20: FALSE | T20: FALSE
A21: Asaas | B21: Brasil | C21: Brasil | D21: Initial Negotiation | E21: PSP/Aggregator | F21: Business Development | G21: Johanderson Guevara | H21: FALSE | I21: FALSE | J21: FALSE | K21: FALSE | L21: FALSE | M21: FALSE | N21: FALSE | O21: FALSE | P21: Tier 3 Partners | Q21: TRUE | R21: FALSE | S21: FALSE | T21: FALSE
A22: AsiaPay | B22: Regional | C22: APAC | D22: Opportunity Identification | E22: PSP/Aggregator | F22: Business Development | G22: Ale/Lily | H22: FALSE | I22: FALSE | J22: FALSE | K22: FALSE | L22: FALSE | M22: FALSE | N22: FALSE | O22: FALSE | P22: Tier 2 Partners | Q22: FALSE | R22: FALSE | S22: FALSE | T22: FALSE
A23: Astropay | B23: Global | C23: Global | D23: Live Partner | E23: APM | F23: Account Management | G23: Alessandra Rospigliosi | H23: FALSE | I23: FALSE | J23: FALSE | K23: TRUE | L23: FALSE | M23: TRUE | N23: FALSE | O23: FALSE | P23: Tier 2 Partners | Q23: TRUE | R23: TRUE | S23: FALSE | T23: TRUE
A24: Au10tix | B24: Global | C24: Global | D24: Agreement Signed | E24: Other | F24: Account Management | G24: Alessandra Rospigliosi | H24: FALSE | I24: TRUE | J24: FALSE | K24: FALSE | L24: FALSE | M24: TRUE | N24: FALSE | O24: TRUE | P24: Non-managed Partners | Q24: TRUE | R24: TRUE | S24: FALSE | T24: FALSE | W24: KYP solution, no se les ha presentado a nadie.
A25: Avenia | B25: Regional | C25: LATAM | D25: Initial Negotiation | E25: BaaS | F25: Business Development | G25: Alessandra Rospigliosi | H25: FALSE | I25: TRUE | K25: FALSE | L25: FALSE | M25: FALSE | N25: FALSE | O25: FALSE | P25: Product Partners (3Ds, Plugins)) | Q25: FALSE | R25: FALSE | S25: FALSE | T25: FALSE
A26: Azify | B26: Global | C26: Global | D26: Opportunity Identification | E26: Other | F26: Business Development | G26: Talita Diaz Gama | H26: FALSE | I26: FALSE | J26: FALSE | K26: FALSE | L26: FALSE | M26: FALSE | N26: FALSE | O26: FALSE | P26: Product Partners (3Ds, Plugins)) | Q26: FALSE | R26: FALSE | S26: FALSE | T26: FALSE | W26: BaaS
A27: Azify | B27: Brasil | C27: Brasil | D27: Opportunity Identification | E27: PSP/Aggregator | F27: Business Development | G27: Johanderson Guevara | H27: FALSE | I27: TRUE | K27: FALSE | L27: FALSE | M27: FALSE | N27: FALSE | O27: FALSE | Q27: FALSE | R27: FALSE | S27: FALSE | T27: FALSE
A28: Azul | B28: Republica Dominicana | C28: LATAM | D28: Lost | E28: Acquirer | F28: Business Development | G28: Daniela Reyes | H28: FALSE | I28: FALSE | J28: FALSE | K28: TRUE | L28: TRUE | M28: FALSE | N28: FALSE | O28: FALSE | P28: Tier 3 Partners | Q28: TRUE | R28: TRUE | S28: FALSE | T28: FALSE | V28: Airtable by Ale
A29: B2E | B29: Brasil | C29: Brasil | D29: Lost | E29: Acquirer | F29: Business Development | G29: Not assigned | H29: FALSE | I29: FALSE | J29: FALSE | K29: FALSE | L29: FALSE | M29: FALSE | N29: FALSE | O29: FALSE | Q29: FALSE | R29: FALSE | S29: FALSE | T29: FALSE
A30: Baaskit | B30: Chile | C30: LATAM | D30: Lost | E30: Acquirer | F30: Business Development | G30: Alessandra Rospigliosi | H30: FALSE | I30: FALSE | J30: FALSE | K30: FALSE | L30: FALSE | M30: FALSE | O30: FALSE | P30: Tier 3 Partners | Q30: FALSE | R30: FALSE | S30: FALSE | T30: FALSE | W30: We will reopen conversations when we have a BC
A31: BAC International Bank | B31: Regional | C31: LATAM | D31: Opportunity Identification | E31: Acquirer | F31: Business Development | G31: Daniela Reyes | H31: TRUE | I31: FALSE | J31: FALSE | K31: TRUE | L31: TRUE | M31: FALSE | N31: FALSE | O31: FALSE | P31: Tier 2 Partners | Q31: TRUE | R31: TRUE | S31: FALSE | T31: FALSE
A32: Bamboo Payments | B32: Global | C32: Global | D32: Live Partner | E32: PSP/Aggregator | F32: Account Management | G32: Talita Diaz Gama | H32: TRUE | I32: FALSE | J32: FALSE | K32: TRUE | L32: TRUE | M32: TRUE | N32: TRUE | O32: FALSE | P32: Tier 2 Partners | Q32: TRUE | R32: TRUE | S32: TRUE | T32: TRUE
A33: Banbajío | B33: Mexico | C33: North America | D33: Lost | E33: Acquirer | F33: Business Development | G33: Daniela Reyes | H33: FALSE | I33: FALSE | J33: FALSE | K33: FALSE | L33: FALSE | M33: FALSE | N33: FALSE | O33: TRUE | P33: Tier 3 Partners | Q33: TRUE | R33: TRUE | S33: FALSE | T33: FALSE
A34: Bancard | B34: Paraguai | C34: LATAM | D34: Opportunity Identification | E34: Acquirer | F34: Business Development | G34: Johanderson Guevara | H34: TRUE | I34: FALSE | K34: FALSE | L34: FALSE | M34: FALSE | N34: FALSE | O34: TRUE | P34: Tier 1 Partners | Q34: FALSE | R34: FALSE | S34: FALSE | T34: FALSE
A35: Banco BHD Leon | B35: Republica Dominicana | C35: LATAM | D35: Opportunity Identification | E35: Acquirer | F35: Business Development | G35: Daniela Reyes | H35: FALSE | I35: FALSE | J35: FALSE | K35: TRUE | L35: FALSE | M35: FALSE | N35: FALSE | O35: FALSE | P35: Tier 3 Partners | Q35: TRUE | R35: TRUE | S35: FALSE | T35: FALSE | V35: Airtable by Ale
A36: Banco Bradesco | B36: Brasil | C36: Brasil | D36: Live Partner | E36: PSP/Aggregator | F36: Business Development | G36: Johanderson Guevara | H36: TRUE | I36: FALSE | J36: FALSE | K36: TRUE | L36: TRUE | M36: FALSE | N36: FALSE | O36: FALSE | P36: Tier 2 Partners | Q36: TRUE | R36: TRUE | S36: FALSE | T36: FALSE
A37: Banco BS2 | B37: Brasil | C37: Brasil | D37: Opportunity Identification | E37: PSP/Aggregator | F37: Business Development | G37: Johanderson Guevara | H37: FALSE | I37: FALSE | J37: FALSE | K37: FALSE | L37: FALSE | M37: FALSE | N37: FALSE | O37: FALSE | P37: Tier 3 Partners | Q37: TRUE | R37: FALSE | S37: FALSE | T37: FALSE
A38: Banco BV | Banly | B38: Brasil | C38: Brasil | D38: Opportunity Identification | E38: PSP/Aggregator | F38: Business Development | G38: Johanderson Guevara | H38: FALSE | I38: TRUE | J38: FALSE | K38: FALSE | L38: FALSE | M38: FALSE | N38: FALSE | O38: FALSE | P38: Tier 3 Partners | Q38: TRUE | R38: FALSE | S38: FALSE | T38: FALSE
A39: Banco de Bogotá | B39: Colombia | C39: LATAM | D39: Opportunity Identification | E39: Acquirer | F39: Business Development | G39: Talita Diaz Gama | H39: TRUE | I39: FALSE | J39: FALSE | K39: FALSE | L39: FALSE | M39: FALSE | N39: FALSE | O39: FALSE | P39: Tier 1 Partners | Q39: TRUE | R39: TRUE | S39: FALSE | T39: FALSE
A40: Banco de Quyaquil | B40: Ecuador | C40: LATAM | D40: Opportunity Identification | E40: Acquirer | F40: Business Development | G40: Daniela Reyes | H40: FALSE | I40: FALSE | J40: FALSE | K40: FALSE | L40: FALSE | M40: FALSE | N40: FALSE | O40: FALSE | P40: Tier 2 Partners | Q40: FALSE | R40: FALSE
A41: Banco do Brasil | B41: Brasil | C41: Brasil | D41: Live Partner | E41: PSP/Aggregator | F41: Account Management | G41: Johanderson Guevara | H41: TRUE | I41: FALSE | J41: FALSE | K41: TRUE | L41: TRUE | M41: TRUE | N41: TRUE | O41: FALSE | P41: Tier 1 Partners | Q41: TRUE | R41: TRUE | S41: FALSE | T41: TRUE | V41: Airtable by Ale
A42: Banco Estado de Chile | B42: Chile | C42: LATAM | D42: Initial Negotiation | E42: Other | F42: Business Development | G42: Talita Diaz Gama | H42: FALSE | I42: FALSE | J42: FALSE | K42: FALSE | L42: FALSE | M42: FALSE | N42: FALSE | O42: FALSE | P42: Tier 3 Partners | Q42: TRUE | R42: TRUE | S42: FALSE | T42: FALSE
A43: Banco Galicia / Nave | B43: Argentina | C43: LATAM | D43: Opportunity Identification | E43: Other | F43: Business Development | G43: Talita Diaz Gama | H43: FALSE | I43: FALSE | J43: FALSE | K43: TRUE | L43: TRUE | M43: FALSE | N43: FALSE | O43: FALSE | P43: Tier 3 Partners | Q43: TRUE | R43: TRUE | S43: FALSE | T43: FALSE | W43: Revisando NDA
A44: Banco Genial | B44: Brasil | C44: Brasil | D44: Lost | E44: Acquirer | F44: Business Development | G44: Not assigned | H44: FALSE | I44: FALSE | J44: FALSE | K44: FALSE | L44: FALSE | M44: FALSE | N44: FALSE | O44: FALSE | Q44: TRUE | R44: FALSE | S44: FALSE | T44: FALSE
A45: Banco Mercantil | B45: Venezuela | C45: LATAM | D45: Opportunity Identification | E45: Acquirer | F45: Business Development | G45: Johanderson Guevara | H45: TRUE | I45: FALSE | K45: FALSE | L45: FALSE | M45: FALSE | N45: FALSE | O45: FALSE | P45: Tier 1 Partners | Q45: FALSE | R45: FALSE
A46: Banco Rendimento | B46: Brasil | C46: Brasil | D46: Lost | E46: Acquirer | F46: Business Development | G46: Not assigned | H46: FALSE | I46: FALSE | J46: FALSE | K46: FALSE | L46: FALSE | M46: FALSE | N46: FALSE | O46: FALSE | Q46: TRUE | R46: TRUE | S46: FALSE | T46: FALSE | V46: Airtable by Ale
A47: Banco Santander (Brasil) S.A. | B47: Brasil | C47: Brasil | D47: Live Partner | E47: PSP/Aggregator | F47: Account Management | G47: Johanderson Guevara | H47: TRUE | I47: FALSE | J47: FALSE | K47: TRUE | L47: TRUE | M47: FALSE | N47: FALSE | O47: FALSE | P47: Tier 2 Partners | Q47: TRUE | R47: TRUE | S47: FALSE | T47: FALSE | V47: Airtable by Ale
A48: Bancolombia | B48: Colombia | C48: LATAM | D48: Initial Negotiation | E48: Acquirer | F48: Business Development | G48: Talita Diaz Gama | H48: TRUE | I48: FALSE | J48: FALSE | K48: FALSE | L48: FALSE | M48: FALSE | N48: FALSE | O48: FALSE | P48: Tier 1 Partners | Q48: TRUE | R48: TRUE
A49: Bancontact | B49: Belgium | C49: EMEA | D49: Initial Negotiation | E49: APM | F49: Business Development | G49: Alessandra Rospigliosi | H49: FALSE | I49: TRUE | J49: FALSE | K49: FALSE | L49: FALSE | M49: FALSE | N49: FALSE | O49: FALSE | P49: Tier 1 Partners | Q49: FALSE | R49: FALSE
A50: Bank Frick | B50: Liechtenstein | C50: EMEA | D50: Only to be integrated | E50: Acquirer | F50: Business Development | G50: Alessandra Rospigliosi | H50: FALSE | I50: FALSE | J50: FALSE | K50: FALSE | L50: FALSE | M50: FALSE | N50: FALSE | O50: FALSE | P50: Tier 3 Partners | Q50: FALSE | R50: FALSE | S50: FALSE | T50: FALSE
A51: Bank of America | B51: USA | C51: North America | D51: Opportunity Identification | E51: Acquirer | F51: Business Development | G51: Daniela Reyes | H51: FALSE | I51: FALSE | J51: FALSE | K51: FALSE | L51: FALSE | M51: FALSE | N51: FALSE | O51: FALSE | P51: Tier 2 Partners | Q51: FALSE | R51: FALSE | S51: FALSE | T51: FALSE
A52: Banorte | B52: Mexico | C52: North America | D52: Initial Negotiation | E52: Acquirer | F52: Business Development | G52: Daniela Reyes | H52: FALSE | I52: FALSE | J52: FALSE | K52: FALSE | L52: FALSE | M52: FALSE | N52: FALSE | O52: FALSE | P52: Tier 2 Partners | Q52: TRUE | R52: TRUE | S52: FALSE | T52: FALSE
A53: Banregio | B53: Mexico | C53: North America | D53: Lost | E53: Acquirer | F53: Business Development | G53: Daniela Reyes | H53: FALSE | I53: FALSE | J53: FALSE | K53: FALSE | L53: FALSE | M53: FALSE | N53: FALSE | O53: FALSE | P53: Tier 3 Partners | Q53: TRUE | R53: TRUE | S53: FALSE | T53: FALSE | V53: Airtable by Ale
A54: Barclays PLC | B54: UK | C54: EMEA | D54: Opportunity Identification | E54: Acquirer | F54: Business Development | G54: Alessandra Rospigliosi | H54: FALSE | I54: FALSE | J54: FALSE | K54: FALSE | L54: FALSE | M54: FALSE | N54: FALSE | O54: FALSE | P54: Tier 1 Partners | Q54: FALSE | R54: FALSE | S54: FALSE | T54: FALSE
A55: Barte | B55: Brasil | C55: Brasil | D55: Agreement Signed | E55: PSP/Aggregator | F55: Account Management | G55: Johanderson Guevara | H55: FALSE | I55: FALSE | J55: FALSE | K55: FALSE | L55: FALSE | M55: TRUE | N55: FALSE | O55: TRUE | P55: Tier 3 Partners | Q55: TRUE | R55: TRUE | S55: FALSE | T55: FALSE | V55: Airtable by Ale
A56: Basis Theory | B56: Global | C56: Global | D56: Agreement Signed - Only referrals | E56: Other | F56: Business Development | G56: Alessandra Rospigliosi | H56: FALSE | I56: TRUE | J56: FALSE | K56: FALSE | L56: FALSE | M56: FALSE | N56: FALSE | O56: TRUE | P56: Product Partners (3Ds, Plugins)) | Q56: FALSE | R56: FALSE | S56: FALSE | T56: FALSE | W56: Just referral agreement, not for integration
A57: Bayonet.io | B57: Regional | C57: LATAM | D57: Agreement Signed | E57: Acquirer | F57: Account Management | G57: Not assigned | H57: FALSE | I57: FALSE | J57: FALSE | K57: TRUE | L57: FALSE | M57: TRUE | N57: FALSE | O57: TRUE | P57: Non-managed Partners | Q57: TRUE | R57: TRUE | S57: FALSE | T57: TRUE
A58: BAZ / Banco Azteca | B58: Mexico | C58: North America | D58: Agreement Signed | E58: Acquirer | F58: Account Management | G58: Daniela Reyes | H58: FALSE | I58: FALSE | J58: FALSE | K58: FALSE | L58: FALSE | M58: TRUE | N58: FALSE | O58: FALSE | P58: Tier 2 Partners | Q58: TRUE | R58: TRUE | S58: FALSE | T58: FALSE | V58: Airtable by Ale
A59: BBVA Colombia | B59: Colombia | C59: LATAM | D59: Initial Negotiation | E59: Acquirer | F59: Business Development | G59: Talita Diaz Gama | H59: TRUE | I59: FALSE | J59: FALSE | K59: FALSE | L59: FALSE | M59: FALSE | N59: FALSE | O59: FALSE | P59: Tier 1 Partners | Q59: TRUE | R59: TRUE
A60: BBVA México | B60: Mexico | C60: North America | D60: Opportunity Identification | E60: Acquirer | F60: Business Development | G60: Daniela Reyes | H60: TRUE | I60: FALSE | J60: FALSE | K60: FALSE | L60: FALSE | M60: FALSE | N60: FALSE | O60: FALSE | P60: Strategic Partners: Very Important | Q60: TRUE | R60: TRUE | S60: FALSE | T60: FALSE | V60: Airtable by Ale
A61: Belvo | B61: Regional | C61: LATAM | D61: Live Partner | E61: APM | F61: Account Management | G61: Talita Diaz Gama | H61: FALSE | I61: FALSE | J61: FALSE | K61: FALSE | L61: FALSE | M61: TRUE | N61: FALSE | O61: FALSE | P61: Tier 3 Partners | Q61: TRUE | R61: TRUE | S61: FALSE | T61: FALSE
A62: Bepsa (Bepsa del Paraguay SAEC) | B62: Paraguai | C62: LATAM | D62: Opportunity Identification | E62: Acquirer | F62: Business Development | G62: Johanderson Guevara | H62: TRUE | I62: FALSE | K62: FALSE | L62: FALSE | M62: FALSE | N62: FALSE | O62: FALSE | P62: Tier 1 Partners | Q62: FALSE | R62: FALSE | S62: FALSE | T62: FALSE
A63: Billdesk | B63: Global | C63: APAC | D63: Agreement Signed | E63: PSP/Aggregator | F63: Account Management | G63: Partha | H63: TRUE | I63: FALSE | J63: FALSE | K63: FALSE | L63: FALSE | M63: FALSE | N63: FALSE | O63: FALSE | P63: Strategic Partners: Very Important | Q63: FALSE | R63: FALSE | S63: FALSE | T63: FALSE | V63: Airtable by Ale
A64: Binance Pay | B64: Global | C64: Global | D64: Agreement Review | E64: APM | F64: Business Development | G64: Francisco Quintana | H64: TRUE | I64: TRUE | J64: Reviewing by compliance | K64: FALSE | L64: FALSE | M64: FALSE | N64: FALSE | O64: FALSE | P64: Tier 1 Partners | Q64: FALSE | R64: FALSE | S64: FALSE | T64: FALSE | U64: Yes | W64: We have sent our agreement back to them with the DPA with comments. Push message to know the status of the agreement and KYP (19.3)
A65: Bitso | B65: Regional | C65: LATAM | D65: Initial Negotiation | E65: Acquirer | F65: Business Development | G65: Daniela Reyes | H65: FALSE | I65: FALSE | K65: FALSE | L65: FALSE | M65: FALSE | N65: FALSE | O65: FALSE | P65: Tier 3 Partners | Q65: TRUE | R65: FALSE | S65: FALSE | T65: FALSE
A66: bKash | B66: Regional | C66: APAC | D66: Lost | E66: Acquirer | F66: Business Development | G66: Not assigned | H66: FALSE | I66: FALSE | K66: FALSE | L66: FALSE | M66: FALSE | N66: FALSE | O66: FALSE | Q66: FALSE | R66: FALSE | S66: FALSE | T66: FALSE
A67: Blik | B67: Poland | C67: EMEA | D67: Initial Negotiation | E67: APM | F67: Business Development | G67: Alessandra Rospigliosi | H67: FALSE | I67: FALSE | J67: FALSE | K67: FALSE | L67: FALSE | M67: FALSE | N67: FALSE | O67: FALSE | P67: Non-managed Partners | Q67: FALSE | R67: FALSE | W67: We cannot integrate them directly if we don't have a PSP license
A68: BlueSnap | B68: Global | C68: Global | D68: Agreement Review | E68: PSP/Aggregator | F68: Business Development | G68: Alessandra Rospigliosi | H68: TRUE | I68: TRUE | J68: FALSE | K68: FALSE | L68: FALSE | M68: FALSE | N68: FALSE | O68: FALSE | P68: Tier 2 Partners | Q68: FALSE | R68: FALSE
A69: Blumonpay | B69: Mexico | C69: North America | D69: Opportunity Identification | E69: Acquirer | F69: Business Development | G69: Daniela Reyes | H69: FALSE | I69: FALSE | K69: FALSE | L69: FALSE | M69: FALSE | N69: FALSE | O69: FALSE | P69: Tier 3 Partners | Q69: FALSE | R69: FALSE | S69: FALSE | T69: FALSE
A70: Boku Inc - New Deal | B70: Global | C70: Global | D70: Initial Negotiation | E70: PSP/Aggregator | F70: Business Development | G70: Ale/Lily | H70: FALSE | I70: FALSE | K70: FALSE | L70: FALSE | M70: FALSE | N70: FALSE | O70: TRUE | P70: Tier 1 Partners | Q70: FALSE | R70: FALSE | S70: FALSE | T70: FALSE | V70: Airtable by Ale
A71: Boomfi | B71: Global | C71: Global | D71: Non-qualified Partner | E71: Acquirer | F71: Business Development | G71: Daniela Reyes | H71: FALSE | I71: FALSE | K71: FALSE | L71: FALSE | M71: FALSE | N71: FALSE | O71: FALSE | P71: Tier 3 Partners | Q71: FALSE | R71: FALSE | S71: FALSE | T71: FALSE
A72: Bren | B72: Brasil | C72: Brasil | D72: Opportunity Identification | E72: Other | F72: Business Development | G72: Johanderson Guevara | H72: FALSE | I72: FALSE | J72: FALSE | K72: FALSE | L72: FALSE | M72: FALSE | N72: FALSE | O72: FALSE | P72: Tier 2 Partners | Q72: FALSE | R72: FALSE | S72: FALSE | T72: FALSE
A73: Brinta | B73: Regional | C73: LATAM | D73: Agreement Signed | E73: PSP/Aggregator | F73: Account Management | G73: Talita Diaz Gama | H73: FALSE | I73: FALSE | K73: FALSE | L73: FALSE | M73: TRUE | N73: FALSE | O73: TRUE | P73: Tier 3 Partners | Q73: TRUE | R73: TRUE | S73: FALSE | T73: FALSE | V73: Airtable by Ale | W73: TAX solution, sirve mas para comercios chicos que no tengan un area contabilidad. Hasta ahora nunca se ha pedido ni se les ha presentado a nadie. Cerramos contrato en 2023.
A74: Brite | B74: Regional | C74: EMEA | D74: Agreement Review | E74: Acquirer | F74: Business Development | G74: Alessandra Rospigliosi | H74: FALSE | I74: TRUE | K74: FALSE | L74: FALSE | M74: FALSE | N74: FALSE | O74: FALSE | P74: Tier 3 Partners | Q74: FALSE | R74: FALSE | S74: FALSE | T74: FALSE | W74: We need UK entity or a business case to close the agreement
A75: BTG Pactual BR | B75: Brasil | C75: Brasil | D75: Agreement Signed | E75: PSP/Aggregator | F75: Account Management | G75: Johanderson Guevara | H75: FALSE | I75: FALSE | K75: FALSE | L75: FALSE | M75: TRUE | N75: FALSE | O75: TRUE | P75: Tier 3 Partners | Q75: TRUE | R75: TRUE | S75: FALSE | T75: FALSE
A76: BVNK | B76: Global | C76: Global | D76: Agreement Signed | E76: PSP/Aggregator | F76: Account Management | G76: Alessandra Rospigliosi | H76: TRUE | I76: FALSE | J76: FALSE | K76: FALSE | L76: FALSE | M76: FALSE | O76: FALSE | P76: Tier 2 Partners | Q76: FALSE | R76: FALSE | S76: FALSE | T76: FALSE
A77: ByBit | B77: Global | C77: Global | D77: Lost | E77: Other | F77: Business Development | G77: Francisco Quintana | H77: FALSE | I77: FALSE | J77: Done | K77: FALSE | L77: FALSE | M77: FALSE | N77: FALSE | O77: FALSE | P77: Tier 3 Partners | Q77: FALSE | R77: FALSE | S77: FALSE | T77: FALSE | U77: No
A78: C6 | B78: Brasil | C78: Brasil | D78: Non-qualified Partner | E78: Other | F78: Business Development | G78: Talita Diaz Gama | H78: FALSE | I78: FALSE | J78: FALSE | K78: FALSE | L78: FALSE | M78: FALSE | N78: FALSE | O78: FALSE | P78: Product Partners (3Ds, Plugins)) | Q78: FALSE | R78: FALSE | S78: FALSE | T78: FALSE | W78: we signed NDA for the POS project in Brazil, this should be product
A79: Carry1st | B79: Regional | C79: Africa | D79: Agreement Signed | E79: Acquirer | F79: Account Management | G79: Alessandra Rospigliosi | H79: FALSE | I79: TRUE | J79: FALSE | K79: FALSE | L79: FALSE | M79: TRUE | N79: FALSE | O79: FALSE | P79: Tier 2 Partners | Q79: FALSE | R79: FALSE | S79: FALSE | T79: FALSE
A80: Cashfree | B80: India | C80: APAC | D80: Agreement Review | E80: PSP/Aggregator | F80: Business Development | G80: Partha | H80: FALSE | I80: FALSE | K80: FALSE | L80: FALSE | M80: FALSE | N80: FALSE | O80: FALSE | P80: Tier 2 Partners | Q80: FALSE | R80: TRUE | S80: FALSE | T80: FALSE | W80: NDA signed. Ask Dani to put me in the thread so we can continue the conversation (16.3)
A81: Celcoin | B81: Brasil | C81: Brasil | D81: Initial Negotiation | E81: PSP/Aggregator | F81: Business Development | G81: Johanderson Guevara | H81: FALSE | I81: FALSE | K81: FALSE | L81: FALSE | M81: FALSE | N81: FALSE | O81: FALSE | P81: Tier 3 Partners | Q81: TRUE | R81: FALSE | S81: FALSE | T81: FALSE
A82: Chargeback 911 | B82: Global | C82: Global | D82: Lost | E82: Acquirer | F82: Business Development | G82: Not assigned | H82: FALSE | I82: FALSE | K82: FALSE | L82: FALSE | M82: FALSE | N82: FALSE | O82: FALSE | Q82: TRUE | R82: TRUE | S82: FALSE | T82: FALSE
A83: Chargeflow | B83: Global | C83: Global | D83: Lost | E83: Acquirer | F83: Business Development | G83: Not assigned | H83: FALSE | I83: TRUE | K83: FALSE | L83: FALSE | M83: FALSE | N83: FALSE | O83: FALSE | Q83: FALSE | R83: FALSE | S83: FALSE | T83: FALSE
A84: Checkout | B84: Global | C84: Global | D84: Live Partner | E84: Acquirer | F84: Account Management | G84: Daniela Reyes | H84: TRUE | I84: FALSE | K84: TRUE | L84: TRUE | M84: TRUE | N84: TRUE | O84: FALSE | P84: Strategic Partners: Very Important | Q84: TRUE | R84: TRUE | S84: FALSE | T84: FALSE | V84: Airtable by Ale
A85: Checkout MENA | B85: Regional | C85: EMEA | D85: Live Partner | E85: Acquirer | F85: Account Management | G85: Francisco Quintana | H85: TRUE | I85: FALSE | J85: Done | K85: TRUE | L85: TRUE | M85: TRUE | N85: TRUE | O85: FALSE | P85: Strategic Partners: Very Important | Q85: TRUE | R85: TRUE | S85: FALSE | T85: FALSE | U85: No | W85: Dani was asking for the lead of Russia and Africa (19.3)
A86: CIBC | B86: Canada | C86: North America | D86: Opportunity Identification | E86: Acquirer | F86: Business Development | G86: Daniela Reyes | H86: FALSE | I86: FALSE | K86: TRUE | L86: TRUE | M86: FALSE | N86: FALSE | O86: FALSE | P86: Tier 3 Partners | Q86: TRUE | R86: TRUE | S86: FALSE | T86: FALSE
A87: Cielo | B87: Brasil | C87: Brasil | D87: Live Partner | E87: Acquirer | F87: Account Management | G87: Talita Diaz Gama | H87: TRUE | I87: FALSE | J87: FALSE | K87: TRUE | L87: TRUE | M87: TRUE | N87: TRUE | O87: FALSE | P87: Strategic Partners: Very Important | Q87: TRUE | R87: TRUE | S87: TRUE | T87: TRUE | W87: Airtable by Ale
A88: Circle | B88: Global | C88: Global | D88: Agreement Signed | E88: Acquirer | F88: Account Management | G88: Daniela Reyes | H88: FALSE | I88: TRUE | K88: FALSE | L88: TRUE | M88: TRUE | N88: FALSE | O88: FALSE | P88: Tier 3 Partners | Q88: FALSE | R88: TRUE | S88: FALSE | T88: FALSE | V88: Airtable by Ale | W88: Crypto, no se les ha presentado a nadie. Firmamos contrato en 2023
A89: Clearbank | B89: Regional | C89: EMEA | D89: Initial Negotiation | E89: BaaS | F89: Business Development | G89: Alessandra Rospigliosi | H89: FALSE | I89: TRUE | K89: FALSE | L89: FALSE | M89: FALSE | N89: FALSE | O89: FALSE | P89: Product Partners (3Ds, Plugins)) | Q89: FALSE | R89: FALSE | S89: FALSE | T89: FALSE
A90: Clearpay | B90: Regional | C90: EMEA | D90: Opportunity Identification | E90: APM | F90: Business Development | G90: Alessandra Rospigliosi | H90: FALSE | I90: FALSE | J90: FALSE | K90: FALSE | L90: FALSE | M90: FALSE | N90: FALSE | O90: FALSE | P90: Tier 2 Partners | Q90: FALSE | R90: FALSE | S90: FALSE | T90: FALSE
A91: ClearSale BR | B91: Brasil | C91: Brasil | D91: Live Partner | E91: Fraud Provider | F91: Account Management | G91: Johanderson Guevara | H91: TRUE | I91: FALSE | J91: FALSE | K91: TRUE | L91: TRUE | M91: TRUE | N91: FALSE | O91: FALSE | P91: Non-managed Partners | Q91: TRUE | R91: FALSE | S91: FALSE | T91: FALSE
A92: ClearSale LATAM | B92: Latam | C92: LATAM | D92: Live Partner | E92: Fraud Provider | F92: Account Management | G92: Talita Diaz Gama | H92: TRUE | I92: TRUE | J92: FALSE | K92: TRUE | L92: TRUE | M92: TRUE | N92: FALSE | O92: FALSE | P92: Non-managed Partners | Q92: TRUE | R92: TRUE | S92: FALSE | T92: FALSE
A93: Cleo | B93: Chile | C93: LATAM | D93: Agreement Signed | E93: Other | F93: Account Management | G93: Talita Diaz Gama | H93: FALSE | I93: TRUE | K93: FALSE | L93: FALSE | M93: TRUE | O93: FALSE | P93: Tier 3 Partners | Q93: FALSE | R93: TRUE | S93: FALSE | T93: FALSE
A94: CMI | B94: Morroco | C94: EMEA | D94: Opportunity Identification | E94: Other | F94: Business Development | G94: Francisco Quintana | H94: FALSE | I94: FALSE | J94: NA | K94: TRUE | L94: FALSE | M94: FALSE | N94: FALSE | O94: FALSE | P94: Tier 3 Partners | Q94: TRUE | R94: TRUE | S94: FALSE | T94: FALSE | U94: No | W94: Ask by Smartfit in the past (They prefer Dlocal) (19.01)
A95: Cobre | B95: Colombia | C95: LATAM | D95: Initial Negotiation | E95: PSP/Aggregator | F95: Business Development | G95: Talita Diaz Gama | H95: FALSE | I95: FALSE | J95: FALSE | K95: FALSE | L95: FALSE | M95: FALSE | N95: FALSE | O95: FALSE | P95: Tier 2 Partners | Q95: TRUE | R95: TRUE | S95: FALSE | T95: FALSE
A96: Cobro Digital | B96: Argentina | C96: LATAM | D96: Live Partner | E96: PSP/Aggregator | F96: Account Management | G96: Talita Diaz Gama | H96: FALSE | I96: FALSE | K96: TRUE | L96: FALSE | M96: TRUE | N96: FALSE | O96: TRUE | P96: Tier 3 Partners | Q96: TRUE | R96: TRUE | S96: FALSE | T96: FALSE | V96: Airtable by Ale
A97: Coda Payment | B97: Regional | C97: Regional | D97: Agreement Review | E97: PSP/Aggregator | F97: Business Development | G97: Fran/Lily | H97: FALSE | I97: FALSE | J97: They havent sent information | K97: FALSE | L97: FALSE | M97: FALSE | N97: FALSE | O97: FALSE | P97: Tier 2 Partners | Q97: FALSE | R97: TRUE | S97: FALSE | T97: FALSE | W97: NDA Signed. Email sent to discuss next steps with them (17.3)
A98: CoinFlow | B98: USA | C98: North America | D98: Agreement Signed | E98: Acquirer | F98: Account Management | G98: Daniela Reyes | H98: TRUE | I98: FALSE | K98: FALSE | L98: FALSE | M98: FALSE | N98: FALSE | O98: FALSE | P98: Tier 3 Partners | Q98: FALSE | R98: FALSE | S98: FALSE | T98: FALSE
A99: Coinpayments | B99: Regional | C99: Global | D99: Initial Negotiation | E99: PSP/Aggregator | F99: Business Development | G99: Not assigned | H99: FALSE | I99: FALSE | K99: FALSE | L99: FALSE | M99: FALSE | N99: FALSE | O99: FALSE | P99: Tier 3 Partners | Q99: FALSE | R99: FALSE | S99: FALSE | T99: FALSE
A100: CoinsPaid | B100: Global | C100: Global | D100: Agreement Signed | E100: PSP/Aggregator | F100: Account Management | G100: Alessandra Rospigliosi | H100: FALSE | I100: FALSE | J100: FALSE | K100: FALSE | L100: FALSE | M100: TRUE | N100: FALSE | O100: FALSE | P100: Tier 2 Partners | Q100: TRUE | R100: TRUE | S100: FALSE | T100: FALSE | W100: Crypto, no se les ha presentado a nadie.
...

Sheet Escalations
A1: Provider | B1: Country | C1: Region | D1: Deal Stage | E1: Partner offering (acquirer, APM, Fraud etc) | F1: Type of Management | G1: Partner Manager | H1: Strategic? | I1: Type of Partner | J1: Comments | K1: Action Required | L1: Next Steps | M1: Dani Read Y/N | N1: Solved
A2: GPay | B2: Turkey | C2: MENAT | D2: Agreement Review | E2: PSP/Aggregator | F2: Business Development | G2: Francisco Quintana | H2: No | I2: Tier 2 Partners | J2: All the information provided in the KYP originates from another company; they are unwilling to disclose their relationship with that entity. There are many red flags, and the provider feels quite sketchy. As a solution, we asked Ugur and Elif to speak with the merchant to see if this volume can be redirected. Dani, I’ve tagged you on the thread with Legal that contains all the detailed information. | K2: We have yet to decide on the final move. Justo already has visibility, but we are aligning expectations and the action plan for this partner is still to be decided | M2: TRUE | N2: Solved
A3: Zain Cash | B3: Iraq | C3: MENAT | D3: Agreement Review | E3: APM | F3: Business Development | G3: Francisco Quintana | H3: No | I3: Tier 2 Partners | J3: We are all ready live with them and we dont have an agreement. Iraq could be a troubled juridiction | K3: We need to aligned with Diego and Justo how to handle this topic and that they introduce us a POC

Sheet Analysis All Hands
B13: Africa | C13: APAC | D13: Brazil | E13: EMEA | F13: Global | G13: LATAM | H13: North America
A14: Opportunity Identification | C14: 5 | D14: 7 | E14: 27 | F14: 8 | G14: 25 | H14: 6
A15: Initial Negotiation | C15: 7 | D15: 3 | E15: 9 | F15: 11 | G15: 10 | H15: 5
A16: Agreement Review | B16: 1 | C16: 19 | D16: 2 | E16: 19 | F16: 17 | G16: 6 | H16: 3
A17: Agreement Signed | B17: 4 | C17: 7 | D17: 13 | E17: 13 | F17: 43 | G17: 34 | H17: 14
A18: Live Partner | C18: 3 | D18: 32 | E18: 1 | F18: 16 | G18: 11 | H18: 3
